pycodon/__init__.py
pycodon/codon_dict.py
pycodon/utils.py
pycodon/metasequence/__init__.py
pycodon/metasequence/utils.py
pycodon/sequence/__init__.py
pycodon/sequence/utils.py
pycodon-0.1.1.dist-info/LICENSE
pycodon-0.1.1.dist-info/METADATA
pycodon-0.1.1.dist-info/WHEEL
pycodon-0.1.1.dist-info/entry_points.txt
pycodon-0.1.1.dist-info/top_level.txt
pycodon-0.1.1.dist-info/RECORD
