Metadata-Version: 2.1
Name: pycodon
Version: 0.1.1
Summary: read DNA sequences
Home-page: https://github.com/tikeeva/pycodon
Author: ['ETikeeva', 'DMalakhova', 'DZanadvornykh']
Author-email: tikeeva_es@mail.ru
License: MIT
Platform: UNKNOWN
Classifier: License :: OSI Approved :: MIT License
Classifier: Programming Language :: Python :: 3.8
Requires-Python: >=3.8.0
License-File: LICENSE
